pycon_co_2025_geopozo/__init__.py
pycon_co_2025_geopozo/dag.py
pycon_co_2025_geopozo/el Asincronismo y la Concurrencia de Python en 2025.py
pycon_co_2025_geopozo/icicle.py
pycon_co_2025_geopozo/py.typed
pycon_co_2025_geopozo-0.9.3.dist-info/METADATA
pycon_co_2025_geopozo-0.9.3.dist-info/WHEEL
pycon_co_2025_geopozo-0.9.3.dist-info/top_level.txt
pycon_co_2025_geopozo-0.9.3.dist-info/RECORD
