Metadata-Version: 2.4
Name: pycon-co-2025-geopozo
Version: 0.9.3
Summary: Talk for pycon-co-2025
Author-email: Andrew Pikul <ajp@grupopikul.com>, David Angarita <david.angarita@grupopikul.com>
Requires-Python: >=3.13
Requires-Dist: graphviz>=0.21
Requires-Dist: marimo>=0.14.9
Requires-Dist: plotly>=6.2.0
Requires-Dist: viztracer>=1.0.4
